rdptools/__init__.py
rdptools/core.py
rdptools-0.1.10.dist-info/WHEEL
rdptools-0.1.10.dist-info/METADATA
rdptools-0.1.10.dist-info/RECORD
