Metadata-Version: 2.1
Name: rdptools
Version: 0.1.10
Summary: 
Author: Baiyue Cao
Author-email: caobaiyue@live.com
Requires-Python: >=3.0.0,<4.0.0
Classifier: Programming Language :: Python :: 3
Classifier: Programming Language :: Python :: 3.4
Classifier: Programming Language :: Python :: 3.5
Classifier: Programming Language :: Python :: 3.6
Classifier: Programming Language :: Python :: 3.7
Classifier: Programming Language :: Python :: 3.8
Classifier: Programming Language :: Python :: 3.9
Requires-Dist: Office365-REST-Python-Client (==2.2.0)
Requires-Dist: geopandas
Requires-Dist: pandas
Requires-Dist: python-dotenv (>=0.14.0,<0.15.0)
